textutils3/__init__.py
textutils3/find_bad_char.py
textutils3/latexdiff.py
textutils3/spellcheck.py
textutils3-1.1.0.dist-info/LICENSE.txt
textutils3-1.1.0.dist-info/METADATA
textutils3-1.1.0.dist-info/WHEEL
textutils3-1.1.0.dist-info/top_level.txt
textutils3-1.1.0.dist-info/RECORD
