Metadata-Version: 2.1
Name: textutils3
Version: 1.1.0
Summary: Recursively check spelling and grammer and other tasks with text documents.
Keywords: spellcheck
Classifier: Development Status :: 5 - Production/Stable
Classifier: Environment :: Console
Classifier: Intended Audience :: End Users/Desktop
Classifier: Operating System :: OS Independent
Classifier: Programming Language :: Python :: 3
Classifier: Topic :: Utilities
Requires-Python: >=3.9
License-File: LICENSE.txt
